LICENSE
MANIFEST.in
README.md
setup.cfg
setup.py
chowkidar/__init__.py
chowkidar/decorators.py
chowkidar/extension.py
chowkidar/models.py
chowkidar/settings.py
chowkidar/view.py
chowkidar/wrappers.py
chowkidar/authentication/__init__.py
chowkidar/authentication/authenticate_with_email.py
chowkidar/authentication/authenticate_with_oauth.py
chowkidar/authentication/authenticate_with_username.py
chowkidar/authentication/oauth/__init__.py
chowkidar/authentication/oauth/handler.py
chowkidar/authentication/oauth/providers.py
chowkidar/authentication/oauth/utils.py
chowkidar/utils/__init__.py
chowkidar/utils/cookie.py
chowkidar/utils/exceptions.py
chowkidar/utils/jwt.py
chowkidar_strawberry.egg-info/PKG-INFO
chowkidar_strawberry.egg-info/SOURCES.txt
chowkidar_strawberry.egg-info/dependency_links.txt
chowkidar_strawberry.egg-info/not-zip-safe
chowkidar_strawberry.egg-info/top_level.txt