Metadata-Version: 2.1
Name: chowkidar-strawberry
Version: 0.3.1
Summary: All-in-One JWT Authentication plugin for Strawberry
Home-page: https://github.com/traboda/chowkidar
Author: Ashwin Shenoy
Author-email: ashwin@traboda.com
Maintainer: Ashwin Shenoy
Maintainer-email: ashwin@traboda.com
License: GNU-GPL-V3
Platform: UNKNOWN
Classifier: Environment :: Web Environment
Classifier: Intended Audience :: Developers
Classifier: Development Status :: 4 - Beta
Classifier: License :: OSI Approved :: GNU General Public License v3 (GPLv3)
Classifier: Operating System :: OS Independent
Classifier: Programming Language :: Python
Classifier: Programming Language :: Python :: 3
Classifier: Programming Language :: Python :: 3.4
Classifier: Programming Language :: Python :: 3.5
Classifier: Programming Language :: Python :: 3.6
Classifier: Programming Language :: Python :: 3.7
Classifier: Programming Language :: Python :: 3.8
Classifier: Framework :: Django
Classifier: Framework :: Django :: 3.0
Classifier: Framework :: Django :: 4.0
License-File: LICENSE
